greatarc/__init__.py
greatarc/location.py
greatarc-0.0.1.dist-info/METADATA
greatarc-0.0.1.dist-info/WHEEL
greatarc-0.0.1.dist-info/top_level.txt
greatarc-0.0.1.dist-info/RECORD
