Metadata-Version: 2.1
Name: greatarc
Version: 0.0.1
Summary: A sample Python package
Home-page: https://github.com/Ziqi-Li/greatarc
Author: Ziqi Li
Author-email: liziqi1992@gmail.com
Classifier: Programming Language :: Python :: 3
Classifier: License :: OSI Approved :: MIT License
Classifier: Operating System :: OS Independent
Requires-Python: >=3.6
